{"generatedAt":1697510823220,"generateTime":10,"contents":[{"_path":"/","_dir":"","_draft":false,"_partial":false,"_locale":"en","title":"Welcome to michiexile.github.io","description":"Some various webapps I have developed","body":{"type":"root","children":[{"type":"element","tag":"h1","props":{"id":"welcome-to-michiexilegithubio"},"children":[{"type":"text","value":"Welcome to "},{"type":"element","tag":"code","props":{"className":""},"children":[{"type":"text","value":"michiexile.github.io"}]}]},{"type":"element","tag":"p","props":{},"children":[{"type":"text","value":"Here, I have gathered a selection of web apps I have developed."}]},{"type":"element","tag":"github-pages-list","props":{"owner":"michiexile"},"children":[]}],"toc":{"title":"","searchDepth":2,"depth":2,"links":[]}},"_type":"markdown","_id":"content:index.md","_source":"content","_file":"index.md","_extension":"md"}],"navigation":[{"title":"Welcome to michiexile.github.io","_path":"/"}]}